Workbook

Sheet Cómo se usa
B2: Cómo se usa esta hoja
B4: 1. Pestaña "Mi línea roja": llena las 3 celdas amarillas de tu cliente y tu presupuesto diario.
B5: Te dice lo máximo que puedes pagar por cada persona que te escribe sin perder dinero.
B6: 2. Cada lunes, abre el Administrador de anuncios, pestaña "Anuncios", y escoge las fechas de la semana pasada.
B7: 3. En "Mis anuncios", una fila por anuncio: copia el gasto, las impresiones, los clics en el enlace y los resultados.
B8: 4. Apunta tú cuántos de esos interesados te compraron. Ese número no lo sabe Meta: solo tú.
B9: 5. Mira la columna "Qué hacer". Verde: déjalo. Rojo: apágalo. Ámbar: cambia la imagen o el gancho.
B11: Las reglas que usa la columna "Qué hacer" son las del capítulo 4.4 de la guía:
B12: · Con menos de 1,000 impresiones es muy pronto para decidir.
B13: · CTR menor de 0.5%: a nadie le interesa. Apágalo.
B14: · Sin resultados después de gastar el doble de tu línea roja: apágalo.
B15: · Costo por resultado igual o menor que tu meta sana: ganador.
B17: Se abre con Excel, con Google Sheets (gratis: Archivo → Importar) o con Numbers.

Sheet Mi línea roja
B2: Mi línea roja
B3: Llena solo las celdas amarillas. Lo demás se calcula solo.
B5: Tu cliente
B6: Lo que te deja un cliente cada vez que te compra | C6: 25 | D6: Lo que te queda a ti, no el precio. Ejemplo: corte de $25.
B7: Cuántas veces te compra al año | C7: 6 | D7: Si es un trabajo de una sola vez (un techo), pon 1.
B8: De cada 10 personas que te escriben, cuántas te compran | C8: 3 | D8: Si no lo sabes, empieza con 2 y corrígelo después.
B10: Tu resultado
B11: Lo que vale un cliente en un año | C11: =C6*C7
B12: LO MÁXIMO que puedes pagar por cada interesado | C12: =C11*C8/10 | D12: Tu línea roja. Por encima de esto, pierdes dinero.
B13: Tu meta sana por interesado (la mitad) | C13: =C12/2 | D13: Si pagas esto o menos, estás ganando bien.
B15: Tu presupuesto
B16: Presupuesto diario de anuncios | C16: 15 | D16: Lo recomendado para empezar: de $15 a $20.
B17: Lo que gastas en una semana | C17: =C16*7
B18: Interesados por semana si pagas tu meta sana | C18: =IFERROR(C17/C13,0) | D18: Es una cuenta de ejemplo, no una promesa.
B19: Clientes nuevos por semana | C19: =C18*C8/10
B20: Lo que te dejan esos clientes en un año | C20: =C19*C11

Sheet Mis anuncios
A1: Mis anuncios
A2: Cada lunes: una fila por anuncio con los números de la semana pasada. Llena las columnas amarillas; las grises se calculan solas. Las 3 primeras filas son un ejemplo: bórralas cuando empieces.
A3: Semana (lunes) | B3: Anuncio | C3: Importe gastado | D3: Impresiones | E3: Clics en el enlace | F3: Resultados | G3: Clientes que te compraron | H3: CTR del enlace | I3: Costo por resultado | J3: Costo por cliente | K3: Ganancia en un año (aprox.) | L3: Qué hacer
A4: 2026-10-12 | B4: R1 · Foto del corte | C4: 70.2 | D4: 5840 | E4: 93 | F4: 9 | G4: 2 | H4: =IF(OR(D4="",D4=0),"",E4/D4) | I4: =IF(OR(C4="",F4="",F4=0),"",C4/F4) | J4: =IF(OR(C4="",G4="",G4=0),"",C4/G4) | K4: =IF(C4="","",G4*'Mi línea roja'!$C$11-C4) | L4: =IF(B4="","",IF(D4<1000,"Muy pronto: espera",IF(H4<0.005,"Apagar: nadie lo toca",IF(AND(F4=0,C4>=2*'Mi línea roja'!$C$12),"Apagar: no trae resultados",IF(F4=0,"Espera: aún sin resultados",IF(I4<='Mi línea roja'!$C$13,"Ganador: déjalo",IF(I4<='Mi línea roja'!$C$12,"Bien: sigue mirando","Caro: cambia la imagen o el gancho")))))))
A5: 2026-10-12 | B5: R1 · Oferta en grande | C5: 45 | D5: 4120 | E5: 45 | F5: 4 | G5: 1 | H5: =IF(OR(D5="",D5=0),"",E5/D5) | I5: =IF(OR(C5="",F5="",F5=0),"",C5/F5) | J5: =IF(OR(C5="",G5="",G5=0),"",C5/G5) | K5: =IF(C5="","",G5*'Mi línea roja'!$C$11-C5) | L5: =IF(B5="","",IF(D5<1000,"Muy pronto: espera",IF(H5<0.005,"Apagar: nadie lo toca",IF(AND(F5=0,C5>=2*'Mi línea roja'!$C$12),"Apagar: no trae resultados",IF(F5=0,"Espera: aún sin resultados",IF(I5<='Mi línea roja'!$C$13,"Ganador: déjalo",IF(I5<='Mi línea roja'!$C$12,"Bien: sigue mirando","Caro: cambia la imagen o el gancho")))))))
A6: 2026-10-12 | B6: R1 · Video 20 segundos | C6: 12.3 | D6: 1950 | E6: 8 | F6: 0 | G6: 0 | H6: =IF(OR(D6="",D6=0),"",E6/D6) | I6: =IF(OR(C6="",F6="",F6=0),"",C6/F6) | J6: =IF(OR(C6="",G6="",G6=0),"",C6/G6) | K6: =IF(C6="","",G6*'Mi línea roja'!$C$11-C6) | L6: =IF(B6="","",IF(D6<1000,"Muy pronto: espera",IF(H6<0.005,"Apagar: nadie lo toca",IF(AND(F6=0,C6>=2*'Mi línea roja'!$C$12),"Apagar: no trae resultados",IF(F6=0,"Espera: aún sin resultados",IF(I6<='Mi línea roja'!$C$13,"Ganador: déjalo",IF(I6<='Mi línea roja'!$C$12,"Bien: sigue mirando","Caro: cambia la imagen o el gancho")))))))
H7: =IF(OR(D7="",D7=0),"",E7/D7) | I7: =IF(OR(C7="",F7="",F7=0),"",C7/F7) | J7: =IF(OR(C7="",G7="",G7=0),"",C7/G7) | K7: =IF(C7="","",G7*'Mi línea roja'!$C$11-C7) | L7: =IF(B7="","",IF(D7<1000,"Muy pronto: espera",IF(H7<0.005,"Apagar: nadie lo toca",IF(AND(F7=0,C7>=2*'Mi línea roja'!$C$12),"Apagar: no trae resultados",IF(F7=0,"Espera: aún sin resultados",IF(I7<='Mi línea roja'!$C$13,"Ganador: déjalo",IF(I7<='Mi línea roja'!$C$12,"Bien: sigue mirando","Caro: cambia la imagen o el gancho")))))))
H8: =IF(OR(D8="",D8=0),"",E8/D8) | I8: =IF(OR(C8="",F8="",F8=0),"",C8/F8) | J8: =IF(OR(C8="",G8="",G8=0),"",C8/G8) | K8: =IF(C8="","",G8*'Mi línea roja'!$C$11-C8) | L8: =IF(B8="","",IF(D8<1000,"Muy pronto: espera",IF(H8<0.005,"Apagar: nadie lo toca",IF(AND(F8=0,C8>=2*'Mi línea roja'!$C$12),"Apagar: no trae resultados",IF(F8=0,"Espera: aún sin resultados",IF(I8<='Mi línea roja'!$C$13,"Ganador: déjalo",IF(I8<='Mi línea roja'!$C$12,"Bien: sigue mirando","Caro: cambia la imagen o el gancho")))))))
H9: =IF(OR(D9="",D9=0),"",E9/D9) | I9: =IF(OR(C9="",F9="",F9=0),"",C9/F9) | J9: =IF(OR(C9="",G9="",G9=0),"",C9/G9) | K9: =IF(C9="","",G9*'Mi línea roja'!$C$11-C9) | L9: =IF(B9="","",IF(D9<1000,"Muy pronto: espera",IF(H9<0.005,"Apagar: nadie lo toca",IF(AND(F9=0,C9>=2*'Mi línea roja'!$C$12),"Apagar: no trae resultados",IF(F9=0,"Espera: aún sin resultados",IF(I9<='Mi línea roja'!$C$13,"Ganador: déjalo",IF(I9<='Mi línea roja'!$C$12,"Bien: sigue mirando","Caro: cambia la imagen o el gancho")))))))
H10: =IF(OR(D10="",D10=0),"",E10/D10) | I10: =IF(OR(C10="",F10="",F10=0),"",C10/F10) | J10: =IF(OR(C10="",G10="",G10=0),"",C10/G10) | K10: =IF(C10="","",G10*'Mi línea roja'!$C$11-C10) | L10: =IF(B10="","",IF(D10<1000,"Muy pronto: espera",IF(H10<0.005,"Apagar: nadie lo toca",IF(AND(F10=0,C10>=2*'Mi línea roja'!$C$12),"Apagar: no trae resultados",IF(F10=0,"Espera: aún sin resultados",IF(I10<='Mi línea roja'!$C$13,"Ganador: déjalo",IF(I10<='Mi línea roja'!$C$12,"Bien: sigue mirando","Caro: cambia la imagen o el gancho")))))))
H11: =IF(OR(D11="",D11=0),"",E11/D11) | I11: =IF(OR(C11="",F11="",F11=0),"",C11/F11) | J11: =IF(OR(C11="",G11="",G11=0),"",C11/G11) | K11: =IF(C11="","",G11*'Mi línea roja'!$C$11-C11) | L11: =IF(B11="","",IF(D11<1000,"Muy pronto: espera",IF(H11<0.005,"Apagar: nadie lo toca",IF(AND(F11=0,C11>=2*'Mi línea roja'!$C$12),"Apagar: no trae resultados",IF(F11=0,"Espera: aún sin resultados",IF(I11<='Mi línea roja'!$C$13,"Ganador: déjalo",IF(I11<='Mi línea roja'!$C$12,"Bien: sigue mirando","Caro: cambia la imagen o el gancho")))))))
H12: =IF(OR(D12="",D12=0),"",E12/D12) | I12: =IF(OR(C12="",F12="",F12=0),"",C12/F12) | J12: =IF(OR(C12="",G12="",G12=0),"",C12/G12) | K12: =IF(C12="","",G12*'Mi línea roja'!$C$11-C12) | L12: =IF(B12="","",IF(D12<1000,"Muy pronto: espera",IF(H12<0.005,"Apagar: nadie lo toca",IF(AND(F12=0,C12>=2*'Mi línea roja'!$C$12),"Apagar: no trae resultados",IF(F12=0,"Espera: aún sin resultados",IF(I12<='Mi línea roja'!$C$13,"Ganador: déjalo",IF(I12<='Mi línea roja'!$C$12,"Bien: sigue mirando","Caro: cambia la imagen o el gancho")))))))
H13: =IF(OR(D13="",D13=0),"",E13/D13) | I13: =IF(OR(C13="",F13="",F13=0),"",C13/F13) | J13: =IF(OR(C13="",G13="",G13=0),"",C13/G13) | K13: =IF(C13="","",G13*'Mi línea roja'!$C$11-C13) | L13: =IF(B13="","",IF(D13<1000,"Muy pronto: espera",IF(H13<0.005,"Apagar: nadie lo toca",IF(AND(F13=0,C13>=2*'Mi línea roja'!$C$12),"Apagar: no trae resultados",IF(F13=0,"Espera: aún sin resultados",IF(I13<='Mi línea roja'!$C$13,"Ganador: déjalo",IF(I13<='Mi línea roja'!$C$12,"Bien: sigue mirando","Caro: cambia la imagen o el gancho")))))))
H14: =IF(OR(D14="",D14=0),"",E14/D14) | I14: =IF(OR(C14="",F14="",F14=0),"",C14/F14) | J14: =IF(OR(C14="",G14="",G14=0),"",C14/G14) | K14: =IF(C14="","",G14*'Mi línea roja'!$C$11-C14) | L14: =IF(B14="","",IF(D14<1000,"Muy pronto: espera",IF(H14<0.005,"Apagar: nadie lo toca",IF(AND(F14=0,C14>=2*'Mi línea roja'!$C$12),"Apagar: no trae resultados",IF(F14=0,"Espera: aún sin resultados",IF(I14<='Mi línea roja'!$C$13,"Ganador: déjalo",IF(I14<='Mi línea roja'!$C$12,"Bien: sigue mirando","Caro: cambia la imagen o el gancho")))))))
H15: =IF(OR(D15="",D15=0),"",E15/D15) | I15: =IF(OR(C15="",F15="",F15=0),"",C15/F15) | J15: =IF(OR(C15="",G15="",G15=0),"",C15/G15) | K15: =IF(C15="","",G15*'Mi línea roja'!$C$11-C15) | L15: =IF(B15="","",IF(D15<1000,"Muy pronto: espera",IF(H15<0.005,"Apagar: nadie lo toca",IF(AND(F15=0,C15>=2*'Mi línea roja'!$C$12),"Apagar: no trae resultados",IF(F15=0,"Espera: aún sin resultados",IF(I15<='Mi línea roja'!$C$13,"Ganador: déjalo",IF(I15<='Mi línea roja'!$C$12,"Bien: sigue mirando","Caro: cambia la imagen o el gancho")))))))
H16: =IF(OR(D16="",D16=0),"",E16/D16) | I16: =IF(OR(C16="",F16="",F16=0),"",C16/F16) | J16: =IF(OR(C16="",G16="",G16=0),"",C16/G16) | K16: =IF(C16="","",G16*'Mi línea roja'!$C$11-C16) | L16: =IF(B16="","",IF(D16<1000,"Muy pronto: espera",IF(H16<0.005,"Apagar: nadie lo toca",IF(AND(F16=0,C16>=2*'Mi línea roja'!$C$12),"Apagar: no trae resultados",IF(F16=0,"Espera: aún sin resultados",IF(I16<='Mi línea roja'!$C$13,"Ganador: déjalo",IF(I16<='Mi línea roja'!$C$12,"Bien: sigue mirando","Caro: cambia la imagen o el gancho")))))))
H17: =IF(OR(D17="",D17=0),"",E17/D17) | I17: =IF(OR(C17="",F17="",F17=0),"",C17/F17) | J17: =IF(OR(C17="",G17="",G17=0),"",C17/G17) | K17: =IF(C17="","",G17*'Mi línea roja'!$C$11-C17) | L17: =IF(B17="","",IF(D17<1000,"Muy pronto: espera",IF(H17<0.005,"Apagar: nadie lo toca",IF(AND(F17=0,C17>=2*'Mi línea roja'!$C$12),"Apagar: no trae resultados",IF(F17=0,"Espera: aún sin resultados",IF(I17<='Mi línea roja'!$C$13,"Ganador: déjalo",IF(I17<='Mi línea roja'!$C$12,"Bien: sigue mirando","Caro: cambia la imagen o el gancho")))))))
H18: =IF(OR(D18="",D18=0),"",E18/D18) | I18: =IF(OR(C18="",F18="",F18=0),"",C18/F18) | J18: =IF(OR(C18="",G18="",G18=0),"",C18/G18) | K18: =IF(C18="","",G18*'Mi línea roja'!$C$11-C18) | L18: =IF(B18="","",IF(D18<1000,"Muy pronto: espera",IF(H18<0.005,"Apagar: nadie lo toca",IF(AND(F18=0,C18>=2*'Mi línea roja'!$C$12),"Apagar: no trae resultados",IF(F18=0,"Espera: aún sin resultados",IF(I18<='Mi línea roja'!$C$13,"Ganador: déjalo",IF(I18<='Mi línea roja'!$C$12,"Bien: sigue mirando","Caro: cambia la imagen o el gancho")))))))
... H203: =IF(OR(D203="",D203=0),"",E203/D203) | I203: =IF(OR(C203="",F203="",F203=0),"",C203/F203) | J203: =IF(OR(C203="",G203="",G203=0),"",C203/G203) | K203: =IF(C203="","",G203*'Mi línea roja'!$C$11-C203) | L203: =IF(B203="","",IF(D203<1000,"Muy pronto: espera",IF(H203<0.005,"Apagar: nadie lo toca",IF(AND(F203=0,C203>=2*'Mi línea roja'!$C$12),"Apagar: no trae resultados",IF(F203=0,"Espera: aún sin resultados",IF(I203<='Mi línea roja'!$C$13,"Ganador: déjalo",IF(I203<='Mi línea roja'!$C$12,"Bien: sigue mirando","Caro: cambia la imagen o el gancho")))))))
